{
  "type": "FeatureCollection",
  "features": [
  {
    "type": "Feature",
    "properties": {
      "name": "Numbs Le Bistro",
      "marker-color": "#A0522D",
      "marker-symbol": "restaurant"
    },
    "geometry": {
      "type": "Point",
      "coordinates": [12.5119765, 41.9229898]
    }
  },
  {
    "type": "Feature",
    "properties": {
      "name": "Pizzeria Montecarlo",
      "marker-color": "#A0522D",
      "marker-symbol": "restaurant"
    },
    "geometry": {
      "type": "Point",
      "coordinates": [12.4781031, 41.9048285]
    }
  },
  {
    "type": "Feature",
    "properties": {
      "name": "Ristorante Leonetti",
      "marker-color": "#A0522D",
      "marker-symbol": "restaurant"
    },
    "geometry": {
      "type": "Point",
      "coordinates": [12.4974552, 41.8983961]
    }
  },
  {
    "type": "Feature",
    "properties": {
      "name": "Elettra",
      "marker-color": "#A0522D",
      "marker-symbol": "restaurant"
    },
    "geometry": {
      "type": "Point",
      "coordinates": [12.4980753, 41.8989567]
    }
  }
  ]
}
